TCLIService/TCLIService.py
TCLIService/__init__.py
TCLIService/constants.py
TCLIService/ttypes.py
pyhive/__init__.py
pyhive/common.py
pyhive/exc.py
pyhive/hive.py
pyhive/presto.py
pyhive/sasl_compat.py
pyhive/sqlalchemy_hive.py
pyhive/sqlalchemy_presto.py
pyhive/sqlalchemy_trino.py
pyhive/trino.py
pyhivefixspark-0.7.0.dist-info/licenses/LICENSE
pyhivefixspark-0.7.0.dist-info/METADATA
pyhivefixspark-0.7.0.dist-info/WHEEL
pyhivefixspark-0.7.0.dist-info/entry_points.txt
pyhivefixspark-0.7.0.dist-info/top_level.txt
pyhivefixspark-0.7.0.dist-info/RECORD
