Metadata-Version: 2.4
Name: PyHiveFixSpark
Version: 0.7.0
Summary: Python interface to Hive
Home-page: https://github.com/dropbox/PyHive
Author: Jing Wang
Author-email: jing@dropbox.com
License: Apache License, Version 2.0
Classifier: Intended Audience :: Developers
Classifier: License :: OSI Approved :: Apache Software License
Classifier: Operating System :: OS Independent
Classifier: Topic :: Database :: Front-Ends
License-File: LICENSE
Requires-Dist: future
Requires-Dist: python-dateutil
Provides-Extra: presto
Requires-Dist: requests>=1.0.0; extra == "presto"
Provides-Extra: trino
Requires-Dist: requests>=1.0.0; extra == "trino"
Provides-Extra: hive
Requires-Dist: sasl>=0.2.1; extra == "hive"
Requires-Dist: thrift>=0.10.0; extra == "hive"
Requires-Dist: thrift_sasl>=0.1.0; extra == "hive"
Provides-Extra: hive-pure-sasl
Requires-Dist: pure-sasl>=0.6.2; extra == "hive-pure-sasl"
Requires-Dist: thrift>=0.10.0; extra == "hive-pure-sasl"
Requires-Dist: thrift_sasl>=0.1.0; extra == "hive-pure-sasl"
Provides-Extra: sqlalchemy
Requires-Dist: sqlalchemy>=1.3.0; extra == "sqlalchemy"
Provides-Extra: kerberos
Requires-Dist: requests_kerberos>=0.12.0; extra == "kerberos"
Dynamic: author
Dynamic: author-email
Dynamic: classifier
Dynamic: description
Dynamic: home-page
Dynamic: license
Dynamic: license-file
Dynamic: provides-extra
Dynamic: requires-dist
Dynamic: summary
